{
  "branch": "feature/process-runtime-reorg",
  "marker_timestamp": "2026-02-08T02:27:06.546789+00:00",
  "summary": "No blocking issues detected. Marker and marker-matched failures summary align to the current commit.",
  "issues": [],
  "follow_ups": [
    "Keep preflight serialized: retro-marker -> collect_failures -> retro_audit_local.",
    "Re-run preflight whenever HEAD changes before senior review launch."
  ],
  "generated_at": "2026-02-08T02:27:15.744903+00:00",
  "mode": "local_commit_aware"
}
